timefuncs/__init__.py
timefuncs/funcs.py
timefuncs-0.1.4.dist-info/LICENSE
timefuncs-0.1.4.dist-info/METADATA
timefuncs-0.1.4.dist-info/WHEEL
timefuncs-0.1.4.dist-info/top_level.txt
timefuncs-0.1.4.dist-info/RECORD
