Metadata-Version: 2.1
Name: timefuncs
Version: 0.1.4
Summary: OWL TIME functions implemented as SPARQL extension functions in rdflib
Home-page: https://github.com/rdflib/timefuncs
Maintainer: Nicholas J. Car
Maintainer-email: nicholas.car@anu.edu.au
License: BSD
Platform: any
Classifier: Programming Language :: Python
Classifier: Programming Language :: Python :: 3
Classifier: Programming Language :: Python :: 3.7
Classifier: Programming Language :: Python :: 3.8
Classifier: Programming Language :: Python :: 3.9
Classifier: License :: OSI Approved :: BSD License
Classifier: Topic :: Software Development :: Libraries :: Python Modules
Classifier: Operating System :: OS Independent
Classifier: Natural Language :: English
License-File: LICENSE
Requires-Dist: rdflib (>=6.0.0)
